django_trojsten_news-0.1.3.dist-info/METADATA
django_trojsten_news-0.1.3.dist-info/metadata.json
django_trojsten_news-0.1.3.dist-info/DESCRIPTION.rst
django_trojsten_news-0.1.3.dist-info/WHEEL
django_trojsten_news-0.1.3.dist-info/top_level.txt
django_trojsten_news-0.1.3.dist-info/RECORD
news/urls.py
news/constants.py
news/views.py
news/tests.py
news/feeds.py
news/__init__.py
news/admin.py
news/models.py
news/migrations/0001_initial.py
news/migrations/__init__.py
news/migrations/0002_auto_20160118_1906.py
news/templates/news/base.html
news/templates/news/index.html
news/templates/news/parts/news_list.html
