Metadata-Version: 2.0
Name: django-trojsten-news
Version: 0.1.3
Summary: News for django, used in Trojsten seminary web apps
Home-page: https://github.com/trojsten/news
Author: Michal Hozza
Author-email: mhozza@gmail.com
License: BSD
Keywords: news
Platform: UNKNOWN
Classifier: Development Status :: 3 - Alpha
Classifier: Framework :: Django
Classifier: Framework :: Django :: 1.8
Classifier: Framework :: Django :: 1.9
Classifier: Intended Audience :: Developers
Classifier: License :: OSI Approved :: BSD License
Classifier: Natural Language :: English
Classifier: Programming Language :: Python :: 2
Classifier: Programming Language :: Python :: 2.7
Classifier: Programming Language :: Python :: 3
Classifier: Programming Language :: Python :: 3.5
Requires-Dist: Django (>=1.8)
Requires-Dist: django-autoslug
Requires-Dist: Markdown
Requires-Dist: django-taggit
Requires-Dist: django-easy-select2
